<?xml version="1.0" encoding="utf-8"?> <Feed BaseUrl = "http://www.pckstudio.tk/studio/PCK/update/" ><Tasks><FileUpdateTask localPath = "\botan32.dll">
		  <Conditions>
		<FileExistsCondition type="not" />
	  </Conditions>
	</FileUpdateTask>
	<FileUpdateTask localPath="\botan64.dll">
		  <Conditions>
		<FileExistsCondition type="not" />
	  </Conditions>
	</FileUpdateTask>
	<FileUpdateTask localPath="\leveldb_LICENSE.txt">
		  <Conditions>
		<FileExistsCondition type="not" />
	  </Conditions>
	</FileUpdateTask>
	<FileUpdateTask localPath="\LevelDB-MCPE-32.dll">
		  <Conditions>
		<FileExistsCondition type="not" />
	  </Conditions>
	</FileUpdateTask>
	<FileUpdateTask localPath="\LevelDB-MCPE-64.dll">
		  <Conditions>
		<FileExistsCondition type="not" />
	  </Conditions>
	</FileUpdateTask>
	<FileUpdateTask localPath="\MCCToolChest.exe">
		  <Conditions>
		<FileExistsCondition type="not" />
	  </Conditions>
	</FileUpdateTask>
	<FileUpdateTask localPath="\MCCToolChest.exe.config">
		  <Conditions>
		<FileExistsCondition type="not" />
	  </Conditions>
	</FileUpdateTask>
	<FileUpdateTask localPath="\NAppUpdate.Framework.dll">
		  <Conditions>
		<FileExistsCondition type="not" />
	  </Conditions>
	</FileUpdateTask>
	<FileUpdateTask localPath="\NBTExplorerWrapper.dll">
		  <Conditions>
		<FileExistsCondition type="not" />
	  </Conditions>
	</FileUpdateTask>
	<FileUpdateTask localPath="\NBTModel.dll">
		  <Conditions>
		<FileExistsCondition type="not" />
	  </Conditions>
	</FileUpdateTask>
	<FileUpdateTask localPath="\Substrate.dll">
		  <Conditions>
		<FileExistsCondition type="not" />
	  </Conditions>
	</FileUpdateTask>
	<FileUpdateTask localPath="\XboxChest.ico">
		  <Conditions>
		<FileExistsCondition type="not" />
	  </Conditions>
	</FileUpdateTask>
	<FileUpdateTask localPath="\XboxHelper32.dll">
		  <Conditions>
		<FileExistsCondition type="not" />
	  </Conditions>
	</FileUpdateTask>
	<FileUpdateTask localPath="\XboxHelper64.dll">
		  <Conditions>
		<FileExistsCondition type="not" />
	  </Conditions>
	</FileUpdateTask>
	<FileUpdateTask localPath="\XBOXSupport32.dll">
		  <Conditions>
		<FileExistsCondition type="not" />
	  </Conditions>
	</FileUpdateTask>
	<FileUpdateTask localPath="\XBOXSupport64.dll">
		  <Conditions>
		<FileExistsCondition type="not" />
	  </Conditions>
	</FileUpdateTask>
	<FileUpdateTask localPath="\support\blocks.json">
		  <Conditions>
		<FileExistsCondition type="not" />
	  </Conditions>
	</FileUpdateTask>
	<FileUpdateTask localPath="\support\blocks.png">
		  <Conditions>
		<FileExistsCondition type="not" />
	  </Conditions>
	</FileUpdateTask>
	<FileUpdateTask localPath="\support\blocks.txt">
		  <Conditions>
		<FileExistsCondition type="not" />
	  </Conditions>
	</FileUpdateTask>
	<FileUpdateTask localPath="\support\blockstates.json">
		  <Conditions>
		<FileExistsCondition type="not" />
	  </Conditions>
	</FileUpdateTask>
	<FileUpdateTask localPath="\support\items.png">
		  <Conditions>
		<FileExistsCondition type="not" />
	  </Conditions>
	</FileUpdateTask>
	<FileUpdateTask localPath="\support\items.txt">
		  <Conditions>
		<FileExistsCondition type="not" />
	  </Conditions>
	</FileUpdateTask>
	<FileUpdateTask localPath="\support\MCCToolChest_Setup.zip">
		  <Conditions>
		<FileExistsCondition type="not" />
	  </Conditions>
	</FileUpdateTask>
	<FileUpdateTask localPath="\support\minecraft.exe">
		  <Conditions>
		<FileExistsCondition type="not" />
	  </Conditions>
	</FileUpdateTask>
	<FileUpdateTask localPath="\support\mobs.png">
		  <Conditions>
		<FileExistsCondition type="not" />
	  </Conditions>
	</FileUpdateTask>
	<FileUpdateTask localPath="\support\professions.png">
		  <Conditions>
		<FileExistsCondition type="not" />
	  </Conditions>
	</FileUpdateTask>
	<FileUpdateTask localPath="">
	  <Conditions>
		<FileExistsCondition type="not" />
	  </Conditions>
	</FileUpdateTask>
  </Tasks>
</Feed>